{"track": [{"idTrack": "33781161", "idAlbum": "2196171", "idArtist": "126728", "idLyric": "119486", "idIMVDB": null, "strTrack": "Crush", "strAlbum": "David Archuleta", "strArtist": "David Archuleta", "strArtistAlternate": null, "intCD": null, "intDuration": "214000", "strGenre": "Pop", "strMood": null, "strStyle": null, "strTheme": null, "strDescriptionEN": null, "strDescriptionDE": null, "strDescriptionFR": null, "strDescriptionCN": null, "strDescriptionIT": null, "strDescriptionJP": null, "strDescriptionRU": null, "strDescriptionES": null, "strDescriptionPT": null, "strDescriptionSE": null, "strDescriptionNL": null, "strDescriptionHU": null, "strDescriptionNO": null, "strDescriptionIL": null, "strDescriptionPL": null, "strTrackThumb": null, "strTrack3DCase": null, "strTrackLyrics": null, "strMusicVid": null, "strMusicVidDirector": null, "strMusicVidCompany": null, "strMusicVidScreen1": null, "strMusicVidScreen2": null, "strMusicVidScreen3": null, "intMusicVidViews": null, "intMusicVidLikes": null, "intMusicVidDislikes": null, "intMusicVidFavorites": null, "intMusicVidComments": null, "intTrackNumber": "1", "intLoved": "0", "intScore": "10", "intScoreVotes": "4", "intTotalListeners": "176494", "intTotalPlays": "1416915", "strMusicBrainzID": "fd130e01-da9f-482a-82f7-8e0d83521498", "strMusicBrainzAlbumID": "a3b2c3b9-e090-333e-bced-344ef88eeff2", "strMusicBrainzArtistID": "150c1fdf-3fc1-4672-93fa-a1aca0a85a53", "strLocked": "Unlocked"}]}