{"track": [{"idTrack": "33762729", "idAlbum": "2194728", "idArtist": "126444", "idLyric": "120399", "idIMVDB": null, "strTrack": "The Time of My Life", "strAlbum": "David Cook", "strArtist": "David Cook", "strArtistAlternate": null, "intCD": null, "intDuration": "216146", "strGenre": null, "strMood": null, "strStyle": null, "strTheme": null, "strDescriptionEN": null, "strDescriptionDE": null, "strDescriptionFR": null, "strDescriptionCN": null, "strDescriptionIT": null, "strDescriptionJP": null, "strDescriptionRU": null, "strDescriptionES": null, "strDescriptionPT": null, "strDescriptionSE": null, "strDescriptionNL": null, "strDescriptionHU": null, "strDescriptionNO": null, "strDescriptionIL": null, "strDescriptionPL": null, "strTrackThumb": null, "strTrack3DCase": null, "strTrackLyrics": null, "strMusicVid": null, "strMusicVidDirector": null, "strMusicVidCompany": null, "strMusicVidScreen1": null, "strMusicVidScreen2": null, "strMusicVidScreen3": null, "intMusicVidViews": null, "intMusicVidLikes": null, "intMusicVidDislikes": null, "intMusicVidFavorites": null, "intMusicVidComments": null, "intTrackNumber": "13", "intLoved": "0", "intScore": "10", "intScoreVotes": "4", "intTotalListeners": "71379", "intTotalPlays": "351911", "strMusicBrainzID": "a9d8d1ad-c5eb-413b-a46a-ae38c2e48374", "strMusicBrainzAlbumID": "60742344-243b-42cb-a851-afd0e247cdb7", "strMusicBrainzArtistID": "966e1095-b172-415c-bae5-53f8041fd050", "strLocked": "Unlocked"}]}