{"track": [{"idTrack": "32785560", "idAlbum": "2115198", "idArtist": "111906", "idLyric": "67822", "idIMVDB": null, "strTrack": "Then", "strAlbum": "American Saturday Night", "strArtist": "Brad Paisley", "strArtistAlternate": null, "intCD": null, "intDuration": "321640", "strGenre": "Country", "strMood": null, "strStyle": null, "strTheme": null, "strDescriptionEN": null, "strDescriptionDE": null, "strDescriptionFR": null, "strDescriptionCN": null, "strDescriptionIT": null, "strDescriptionJP": null, "strDescriptionRU": null, "strDescriptionES": null, "strDescriptionPT": null, "strDescriptionSE": null, "strDescriptionNL": null, "strDescriptionHU": null, "strDescriptionNO": null, "strDescriptionIL": null, "strDescriptionPL": null, "strTrackThumb": null, "strTrack3DCase": null, "strTrackLyrics": null, "strMusicVid": null, "strMusicVidDirector": null, "strMusicVidCompany": null, "strMusicVidScreen1": null, "strMusicVidScreen2": null, "strMusicVidScreen3": null, "intMusicVidViews": null, "intMusicVidLikes": null, "intMusicVidDislikes": null, "intMusicVidFavorites": null, "intMusicVidComments": null, "intTrackNumber": "4", "intLoved": "0", "intScore": null, "intScoreVotes": null, "intTotalListeners": "121352", "intTotalPlays": "411568", "strMusicBrainzID": "e061aa59-f069-43a5-9aee-eaa5483990e5", "strMusicBrainzAlbumID": "ad428872-2b62-407e-a8a9-4a04439ab1f7", "strMusicBrainzArtistID": "6cfd7ffc-824f-4219-8e27-4b9417700f44", "strLocked": "Unlocked"}]}