{"track": [{"idTrack": "32804442", "idAlbum": "2116808", "idArtist": "112200", "idLyric": "102477", "idIMVDB": null, "strTrack": "December", "strAlbum": "Collective Soul", "strArtist": "Collective Soul", "strArtistAlternate": null, "intCD": null, "intDuration": "285373", "strGenre": null, "strMood": null, "strStyle": null, "strTheme": null, "strDescriptionEN": null, "strDescriptionDE": null, "strDescriptionFR": null, "strDescriptionCN": null, "strDescriptionIT": null, "strDescriptionJP": null, "strDescriptionRU": null, "strDescriptionES": null, "strDescriptionPT": null, "strDescriptionSE": null, "strDescriptionNL": null, "strDescriptionHU": null, "strDescriptionNO": null, "strDescriptionIL": null, "strDescriptionPL": null, "strTrackThumb": null, "strTrack3DCase": null, "strTrackLyrics": null, "strMusicVid": null, "strMusicVidDirector": "Lynn Spinnato", "strMusicVidCompany": "", "strMusicVidScreen1": null, "strMusicVidScreen2": null, "strMusicVidScreen3": null, "intMusicVidViews": null, "intMusicVidLikes": null, "intMusicVidDislikes": null, "intMusicVidFavorites": null, "intMusicVidComments": null, "intTrackNumber": "5", "intLoved": "0", "intScore": "10", "intScoreVotes": "5", "intTotalListeners": "238836", "intTotalPlays": "970125", "strMusicBrainzID": "96d402df-2f47-4874-b27b-d2b2a8de1878", "strMusicBrainzAlbumID": "0652191a-7e84-4b1d-8677-d352d2021353", "strMusicBrainzArtistID": "aa266ac7-d919-4132-982e-76cbd95591a7", "strLocked": "Unlocked"}]}