{"track": [{"idTrack": "33777490", "idAlbum": "2195866", "idArtist": "111907", "idLyric": "0", "idIMVDB": null, "strTrack": "Bottoms Up", "strAlbum": "Bottoms Up", "strArtist": "Brantley Gilbert", "strArtistAlternate": null, "intCD": null, "intDuration": "219000", "strGenre": null, "strMood": null, "strStyle": null, "strTheme": null, "strDescriptionEN": null, "strDescriptionDE": null, "strDescriptionFR": null, "strDescriptionCN": null, "strDescriptionIT": null, "strDescriptionJP": null, "strDescriptionRU": null, "strDescriptionES": null, "strDescriptionPT": null, "strDescriptionSE": null, "strDescriptionNL": null, "strDescriptionHU": null, "strDescriptionNO": null, "strDescriptionIL": null, "strDescriptionPL": null, "strTrackThumb": null, "strTrack3DCase": null, "strTrackLyrics": null, "strMusicVid": null, "strMusicVidDirector": null, "strMusicVidCompany": null, "strMusicVidScreen1": null, "strMusicVidScreen2": null, "strMusicVidScreen3": null, "intMusicVidViews": null, "intMusicVidLikes": null, "intMusicVidDislikes": null, "intMusicVidFavorites": null, "intMusicVidComments": null, "intTrackNumber": "1", "intLoved": "0", "intScore": "10", "intScoreVotes": "3", "intTotalListeners": "47848", "intTotalPlays": "289601", "strMusicBrainzID": "c2f068bb-ada5-4ded-a5a7-915de0514c01", "strMusicBrainzAlbumID": "8157307b-cb76-4c87-8d40-cb8b2e26ce9a", "strMusicBrainzArtistID": "9ad8aede-6938-48f2-93fa-908bc4da9ef6", "strLocked": "Unlocked"}]}