{"track": [{"idTrack": "34627557", "idAlbum": "2266288", "idArtist": "111912", "idLyric": null, "idIMVDB": null, "strTrack": "Beer for My Horses", "strAlbum": "Greatest Hits 2", "strArtist": "Toby Keith", "strArtistAlternate": null, "intCD": null, "intDuration": "212333", "strGenre": null, "strMood": null, "strStyle": null, "strTheme": null, "strDescriptionEN": null, "strDescriptionDE": null, "strDescriptionFR": null, "strDescriptionCN": null, "strDescriptionIT": null, "strDescriptionJP": null, "strDescriptionRU": null, "strDescriptionES": null, "strDescriptionPT": null, "strDescriptionSE": null, "strDescriptionNL": null, "strDescriptionHU": null, "strDescriptionNO": null, "strDescriptionIL": null, "strDescriptionPL": null, "strTrackThumb": null, "strTrack3DCase": null, "strTrackLyrics": null, "strMusicVid": null, "strMusicVidDirector": null, "strMusicVidCompany": null, "strMusicVidScreen1": null, "strMusicVidScreen2": null, "strMusicVidScreen3": null, "intMusicVidViews": null, "intMusicVidLikes": null, "intMusicVidDislikes": null, "intMusicVidFavorites": null, "intMusicVidComments": null, "intTrackNumber": "9", "intLoved": "0", "intScore": "10", "intScoreVotes": "4", "intTotalListeners": "194602", "intTotalPlays": "547179", "strMusicBrainzID": "c88fc0b6-adea-4cb5-b2a4-9370ce54e1a1", "strMusicBrainzAlbumID": "245b3cb8-1f89-3aee-84c3-1acc6bdb168d", "strMusicBrainzArtistID": "2f951906-5629-4fef-a260-5033151c162a", "strLocked": "Unlocked"}]}