{"track": [{"idTrack": "32870211", "idAlbum": "2121935", "idArtist": "112991", "idLyric": "195441", "idIMVDB": null, "strTrack": "In Those Jeans", "strAlbum": "The Senior", "strArtist": "Ginuwine", "strArtistAlternate": null, "intCD": null, "intDuration": "243440", "strGenre": "R&B", "strMood": null, "strStyle": null, "strTheme": null, "strDescriptionEN": null, "strDescriptionDE": null, "strDescriptionFR": null, "strDescriptionCN": null, "strDescriptionIT": null, "strDescriptionJP": null, "strDescriptionRU": null, "strDescriptionES": null, "strDescriptionPT": null, "strDescriptionSE": null, "strDescriptionNL": null, "strDescriptionHU": null, "strDescriptionNO": null, "strDescriptionIL": null, "strDescriptionPL": null, "strTrackThumb": null, "strTrack3DCase": null, "strTrackLyrics": null, "strMusicVid": null, "strMusicVidDirector": "Chris Robinson", "strMusicVidCompany": "", "strMusicVidScreen1": null, "strMusicVidScreen2": null, "strMusicVidScreen3": null, "intMusicVidViews": null, "intMusicVidLikes": null, "intMusicVidDislikes": null, "intMusicVidFavorites": null, "intMusicVidComments": null, "intTrackNumber": "5", "intLoved": "0", "intScore": "10", "intScoreVotes": "4", "intTotalListeners": "197844", "intTotalPlays": "516176", "strMusicBrainzID": "6f6b45e3-b592-47b0-9edc-8a680cd92af7", "strMusicBrainzAlbumID": "51f27513-b2aa-3676-af54-217005f1084b", "strMusicBrainzArtistID": "9e5fd95d-c0c1-412c-be11-06e7fbe99556", "strLocked": "Unlocked"}]}