{"track": [{"idTrack": "35457178", "idAlbum": "2342811", "idArtist": "159218", "idLyric": null, "idIMVDB": null, "strTrack": "Roxanne", "strAlbum": "Roxanne", "strArtist": "Arizona Zervas", "strArtistAlternate": null, "intCD": null, "intDuration": "163000", "strGenre": "", "strMood": "...", "strStyle": "...", "strTheme": "...", "strDescriptionEN": "", "strDescriptionDE": null, "strDescriptionFR": null, "strDescriptionCN": null, "strDescriptionIT": null, "strDescriptionJP": null, "strDescriptionRU": null, "strDescriptionES": null, "strDescriptionPT": null, "strDescriptionSE": null, "strDescriptionNL": null, "strDescriptionHU": null, "strDescriptionNO": null, "strDescriptionIL": null, "strDescriptionPL": null, "strTrackThumb": null, "strTrack3DCase": null, "strTrackLyrics": "", "strMusicVid": "https://www.youtube.com/watch?v=16YnOUnbE6s", "strMusicVidDirector": "", "strMusicVidCompany": "", "strMusicVidScreen1": null, "strMusicVidScreen2": null, "strMusicVidScreen3": null, "intMusicVidViews": "95106046", "intMusicVidLikes": "1431048", "intMusicVidDislikes": "38735", "intMusicVidFavorites": "0", "intMusicVidComments": "55327", "intTrackNumber": "1", "intLoved": "0", "intScore": null, "intScoreVotes": null, "intTotalListeners": null, "intTotalPlays": null, "strMusicBrainzID": "5bddd95d-03c5-4c9f-b241-cfc8fcaa1172", "strMusicBrainzAlbumID": "a2b411f4-3991-4cb6-abdf-e375c0b01444", "strMusicBrainzArtistID": "aa4296e3-f61c-46b5-b4fa-abce5bb62ffb", "strLocked": "Unlocked"}]}