{"track": [{"idTrack": "36209987", "idAlbum": "2417119", "idArtist": "114415", "idLyric": null, "idIMVDB": null, "strTrack": "Enemy", "strAlbum": "Imagine Dragons live in Vegas", "strArtist": "Imagine Dragons", "strArtistAlternate": null, "intCD": null, "intDuration": "233000", "strGenre": null, "strMood": null, "strStyle": null, "strTheme": null, "strDescriptionEN": null, "strDescriptionDE": null, "strDescriptionFR": null, "strDescriptionCN": null, "strDescriptionIT": null, "strDescriptionJP": null, "strDescriptionRU": null, "strDescriptionES": null, "strDescriptionPT": null, "strDescriptionSE": null, "strDescriptionNL": null, "strDescriptionHU": null, "strDescriptionNO": null, "strDescriptionIL": null, "strDescriptionPL": null, "strTrackThumb": null, "strTrack3DCase": null, "strTrackLyrics": null, "strMusicVid": null, "strMusicVidDirector": null, "strMusicVidCompany": null, "strMusicVidScreen1": null, "strMusicVidScreen2": null, "strMusicVidScreen3": null, "intMusicVidViews": null, "intMusicVidLikes": null, "intMusicVidDislikes": null, "intMusicVidFavorites": null, "intMusicVidComments": null, "intTrackNumber": "17", "intLoved": "0", "intScore": null, "intScoreVotes": null, "intTotalListeners": null, "intTotalPlays": null, "strMusicBrainzID": "35ef1104-44af-43f7-a91a-159bb9df0cb0", "strMusicBrainzAlbumID": "bc56f4c1-1724-4fa7-873c-dc088323a502", "strMusicBrainzArtistID": "012151a8-0f9a-44c9-997f-ebd68b5389f9", "strLocked": "Unlocked"}]}