{"track": [{"idTrack": "32769910", "idAlbum": "2113957", "idArtist": "111651", "idLyric": "0", "idIMVDB": null, "strTrack": "Nothin' on You", "strAlbum": "B.o.B Presents: The Adventures of Bobby Ray", "strArtist": "B.o.B", "strArtistAlternate": "BOB", "intCD": null, "intDuration": "271626", "strGenre": "Hip-Hop", "strMood": null, "strStyle": null, "strTheme": null, "strDescriptionEN": "\"Nothin' on You\" is the debut single by American rapper B.o.B. The song features vocals from Bruno Mars. The song is included in B.o.B's debut studio album B.o.B Presents: The Adventures of Bobby Ray. An official remix version of this song, which features Big Boi, debuted on March 21, 2010. The song reached number one in the Netherlands, the United Kingdom and the United States. The song was nominated for three Grammys, including Record of the Year, on December 1, 2010 for the 53rd Grammy Awards.", "strDescriptionDE": null, "strDescriptionFR": null, "strDescriptionCN": null, "strDescriptionIT": null, "strDescriptionJP": null, "strDescriptionRU": null, "strDescriptionES": null, "strDescriptionPT": null, "strDescriptionSE": null, "strDescriptionNL": null, "strDescriptionHU": null, "strDescriptionNO": null, "strDescriptionIL": null, "strDescriptionPL": null, "strTrackThumb": "https://www.theaudiodb.com/images/media/track/thumb/tyrwpv1359088549.jpg", "strTrack3DCase": null, "strTrackLyrics": "", "strMusicVid": "http://www.youtube.com/watch?v=8PTDv_szmL0", "strMusicVidDirector": "Ethan Lader", "strMusicVidCompany": "", "strMusicVidScreen1": null, "strMusicVidScreen2": null, "strMusicVidScreen3": null, "intMusicVidViews": "131697674", "intMusicVidLikes": "349172", "intMusicVidDislikes": "6035", "intMusicVidFavorites": null, "intMusicVidComments": null, "intTrackNumber": "2", "intLoved": "0", "intScore": null, "intScoreVotes": null, "intTotalListeners": null, "intTotalPlays": null, "strMusicBrainzID": "ff701bef-2637-4463-b76d-8ad1a60b3036", "strMusicBrainzAlbumID": "dfc3df85-c536-45e5-95a2-b423ee92a103", "strMusicBrainzArtistID": "94c338ff-1985-4429-9dc8-997b61bb5932", "strLocked": "Unlocked"}]}