{"track": [{"idTrack": "34773283", "idAlbum": "2277748", "idArtist": "112696", "idLyric": null, "idIMVDB": null, "strTrack": "When You Believe", "strAlbum": "The Ultimate Collection", "strArtist": "Whitney Houston", "strArtistAlternate": null, "intCD": null, "intDuration": "273320", "strGenre": null, "strMood": null, "strStyle": null, "strTheme": null, "strDescriptionEN": null, "strDescriptionDE": null, "strDescriptionFR": null, "strDescriptionCN": null, "strDescriptionIT": null, "strDescriptionJP": null, "strDescriptionRU": null, "strDescriptionES": null, "strDescriptionPT": null, "strDescriptionSE": null, "strDescriptionNL": null, "strDescriptionHU": null, "strDescriptionNO": null, "strDescriptionIL": null, "strDescriptionPL": null, "strTrackThumb": null, "strTrack3DCase": null, "strTrackLyrics": null, "strMusicVid": null, "strMusicVidDirector": null, "strMusicVidCompany": null, "strMusicVidScreen1": null, "strMusicVidScreen2": null, "strMusicVidScreen3": null, "intMusicVidViews": null, "intMusicVidLikes": null, "intMusicVidDislikes": null, "intMusicVidFavorites": null, "intMusicVidComments": null, "intTrackNumber": "8", "intLoved": "0", "intScore": null, "intScoreVotes": null, "intTotalListeners": null, "intTotalPlays": null, "strMusicBrainzID": "fca5f8c4-dac5-47a2-9658-cf2409bad4f6", "strMusicBrainzAlbumID": "298bf966-94f6-302d-9489-8a4ff262eb93", "strMusicBrainzArtistID": "0307edfc-437c-4b48-8700-80680e66a228", "strLocked": "Unlocked"}]}