{"track": [{"idTrack": "33969080", "idAlbum": "2211638", "idArtist": "130255", "idLyric": "268396", "idIMVDB": null, "strTrack": "The Way I Feel About You", "strAlbum": "Ritual of Love", "strArtist": "Karyn White", "strArtistAlternate": null, "intCD": null, "intDuration": "275293", "strGenre": "Soul", "strMood": null, "strStyle": null, "strTheme": null, "strDescriptionEN": null, "strDescriptionDE": null, "strDescriptionFR": null, "strDescriptionCN": null, "strDescriptionIT": null, "strDescriptionJP": null, "strDescriptionRU": null, "strDescriptionES": null, "strDescriptionPT": null, "strDescriptionSE": null, "strDescriptionNL": null, "strDescriptionHU": null, "strDescriptionNO": null, "strDescriptionIL": null, "strDescriptionPL": null, "strTrackThumb": null, "strTrack3DCase": null, "strTrackLyrics": null, "strMusicVid": null, "strMusicVidDirector": null, "strMusicVidCompany": null, "strMusicVidScreen1": null, "strMusicVidScreen2": null, "strMusicVidScreen3": null, "intMusicVidViews": null, "intMusicVidLikes": null, "intMusicVidDislikes": null, "intMusicVidFavorites": null, "intMusicVidComments": null, "intTrackNumber": "3", "intLoved": "0", "intScore": "10", "intScoreVotes": "4", "intTotalListeners": "19789", "intTotalPlays": "43792", "strMusicBrainzID": "5d1c1f1b-0f81-4c96-b575-68fd9c138ec0", "strMusicBrainzAlbumID": "33a3c309-0ef3-326e-a3a2-3db6247788fe", "strMusicBrainzArtistID": "2258c0cf-77d7-4ddd-9440-f36e3c7a5e22", "strLocked": "Unlocked"}]}