{"track": [{"idTrack": "32765533", "idAlbum": "2113586", "idArtist": "111592", "idLyric": "534422", "idIMVDB": "105181211009", "strTrack": "Gone Till November", "strAlbum": "Presents the Carnival Featuring the Refugee Allstars", "strArtist": "Wyclef Jean", "strArtistAlternate": null, "intCD": null, "intDuration": "207000", "strGenre": "Hip-Hop", "strMood": "...", "strStyle": "Reggae", "strTheme": "...", "strDescriptionEN": null, "strDescriptionDE": null, "strDescriptionFR": null, "strDescriptionCN": null, "strDescriptionIT": null, "strDescriptionJP": null, "strDescriptionRU": null, "strDescriptionES": null, "strDescriptionPT": null, "strDescriptionSE": null, "strDescriptionNL": null, "strDescriptionHU": null, "strDescriptionNO": null, "strDescriptionIL": null, "strDescriptionPL": null, "strTrackThumb": "https://www.theaudiodb.com/images/media/track/thumb/c5n6wp1670778672.jpg", "strTrack3DCase": null, "strTrackLyrics": null, "strMusicVid": "https://www.youtube.com/watch?v=kI6MWZrl8v8", "strMusicVidDirector": "Francis Lawrence", "strMusicVidCompany": "", "strMusicVidScreen1": null, "strMusicVidScreen2": null, "strMusicVidScreen3": null, "intMusicVidViews": "10523851", "intMusicVidLikes": "59292", "intMusicVidDislikes": null, "intMusicVidFavorites": "0", "intMusicVidComments": "3209", "intTrackNumber": "10", "intLoved": "0", "intScore": "10", "intScoreVotes": "4", "intTotalListeners": "100020", "intTotalPlays": "357656", "strMusicBrainzID": "5b41de4f-7003-41af-ab01-dd38e5d69597", "strMusicBrainzAlbumID": "e2ffa278-c47d-321b-a7a9-b7dbd655929c", "strMusicBrainzArtistID": "4f29ecd7-21a5-4c03-b9ba-d0cfe9488f8c", "strLocked": "Unlocked"}]}