{"track": [{"idTrack": "33637220", "idAlbum": "2184582", "idArtist": "124544", "idLyric": "502491", "idIMVDB": null, "strTrack": "Westside", "strAlbum": "They Never Saw Me Coming", "strArtist": "TQ", "strArtistAlternate": null, "intCD": null, "intDuration": "304733", "strGenre": "R&B", "strMood": null, "strStyle": null, "strTheme": null, "strDescriptionEN": null, "strDescriptionDE": null, "strDescriptionFR": null, "strDescriptionCN": null, "strDescriptionIT": null, "strDescriptionJP": null, "strDescriptionRU": null, "strDescriptionES": null, "strDescriptionPT": null, "strDescriptionSE": null, "strDescriptionNL": null, "strDescriptionHU": null, "strDescriptionNO": null, "strDescriptionIL": null, "strDescriptionPL": null, "strTrackThumb": null, "strTrack3DCase": null, "strTrackLyrics": null, "strMusicVid": null, "strMusicVidDirector": "Darren Grant", "strMusicVidCompany": "Shooting Star Pictures", "strMusicVidScreen1": null, "strMusicVidScreen2": null, "strMusicVidScreen3": null, "intMusicVidViews": null, "intMusicVidLikes": null, "intMusicVidDislikes": null, "intMusicVidFavorites": null, "intMusicVidComments": null, "intTrackNumber": "2", "intLoved": "0", "intScore": "10", "intScoreVotes": "3", "intTotalListeners": "41207", "intTotalPlays": "148413", "strMusicBrainzID": "0b22c1ce-6b55-4a84-8547-db269c41661d", "strMusicBrainzAlbumID": "1ab7468c-e345-362b-b735-d3942631c755", "strMusicBrainzArtistID": "fe47130b-6abd-403e-8829-42f55a21a086", "strLocked": "Unlocked"}]}