{"track": [{"idTrack": "32865514", "idAlbum": "2121586", "idArtist": "112932", "idLyric": "119006", "idIMVDB": null, "strTrack": "It's Not Over", "strAlbum": "Daughtry", "strArtist": "Daughtry", "strArtistAlternate": "DAUGHTRY", "intCD": null, "intDuration": "215000", "strGenre": "Alternative Rock", "strMood": null, "strStyle": null, "strTheme": null, "strDescriptionEN": "\"It's Not Over\" is the first official single from Daughtry's first album, Daughtry. The song was used as a teaser to the second season fall finale of Prison Break. It was certified Platinum in April 2007. As of August 2007 it was in the top ten digital selling songs of the year.", "strDescriptionDE": null, "strDescriptionFR": null, "strDescriptionCN": null, "strDescriptionIT": null, "strDescriptionJP": null, "strDescriptionRU": null, "strDescriptionES": null, "strDescriptionPT": null, "strDescriptionSE": null, "strDescriptionNL": null, "strDescriptionHU": null, "strDescriptionNO": null, "strDescriptionIL": null, "strDescriptionPL": null, "strTrackThumb": "https://www.theaudiodb.com/images/media/track/thumb/vyryuy1374055217.jpg", "strTrack3DCase": null, "strTrackLyrics": "", "strMusicVid": "http://www.youtube.com/watch?v=UQ92eyxnxmQ", "strMusicVidDirector": "Dean Karr", "strMusicVidCompany": "Karma", "strMusicVidScreen1": null, "strMusicVidScreen2": null, "strMusicVidScreen3": null, "intMusicVidViews": "23236509", "intMusicVidLikes": "85205", "intMusicVidDislikes": "1114", "intMusicVidFavorites": null, "intMusicVidComments": null, "intTrackNumber": "1", "intLoved": "2", "intScore": "10", "intScoreVotes": "4", "intTotalListeners": "436161", "intTotalPlays": "2514059", "strMusicBrainzID": "f9462766-8938-4bb8-8d4a-1d4f5d4b0144", "strMusicBrainzAlbumID": "a89eb3b6-efe2-3d03-86c1-7e88f66695d3", "strMusicBrainzArtistID": "21e3292e-dac8-4609-b57d-402f926aa41f", "strLocked": "Unlocked"}]}