{"track": [{"idTrack": "33115254", "idAlbum": "2141853", "idArtist": "116343", "idLyric": "154966", "idIMVDB": null, "strTrack": "Wait for You", "strAlbum": "Elliott Yamin", "strArtist": "Elliott Yamin", "strArtistAlternate": null, "intCD": null, "intDuration": "261320", "strGenre": "Pop", "strMood": null, "strStyle": null, "strTheme": null, "strDescriptionEN": null, "strDescriptionDE": null, "strDescriptionFR": null, "strDescriptionCN": null, "strDescriptionIT": null, "strDescriptionJP": null, "strDescriptionRU": null, "strDescriptionES": null, "strDescriptionPT": null, "strDescriptionSE": null, "strDescriptionNL": null, "strDescriptionHU": null, "strDescriptionNO": null, "strDescriptionIL": null, "strDescriptionPL": null, "strTrackThumb": null, "strTrack3DCase": null, "strTrackLyrics": null, "strMusicVid": null, "strMusicVidDirector": null, "strMusicVidCompany": null, "strMusicVidScreen1": null, "strMusicVidScreen2": null, "strMusicVidScreen3": null, "intMusicVidViews": null, "intMusicVidLikes": null, "intMusicVidDislikes": null, "intMusicVidFavorites": null, "intMusicVidComments": null, "intTrackNumber": "2", "intLoved": "0", "intScore": "10", "intScoreVotes": "4", "intTotalListeners": "112950", "intTotalPlays": "691520", "strMusicBrainzID": "4e4662c0-9772-436a-9d93-24c4b46ee0f2", "strMusicBrainzAlbumID": "25f1b0ea-7791-385b-b891-c6ad0404551b", "strMusicBrainzArtistID": "f1c1963a-ba17-4c61-b4d5-344aec12e1c0", "strLocked": "Unlocked"}]}