{"track": [{"idTrack": "33224598", "idAlbum": "2150668", "idArtist": "117736", "idLyric": "0", "idIMVDB": null, "strTrack": "It's Over Now", "strAlbum": "Part III", "strArtist": "112", "strArtistAlternate": null, "intCD": null, "intDuration": "264933", "strGenre": "R&B", "strMood": null, "strStyle": null, "strTheme": null, "strDescriptionEN": null, "strDescriptionDE": null, "strDescriptionFR": null, "strDescriptionCN": null, "strDescriptionIT": null, "strDescriptionJP": null, "strDescriptionRU": null, "strDescriptionES": null, "strDescriptionPT": null, "strDescriptionSE": null, "strDescriptionNL": null, "strDescriptionHU": null, "strDescriptionNO": null, "strDescriptionIL": null, "strDescriptionPL": null, "strTrackThumb": null, "strTrack3DCase": null, "strTrackLyrics": null, "strMusicVid": null, "strMusicVidDirector": "Chris Robinson", "strMusicVidCompany": "Squeak Pictures", "strMusicVidScreen1": null, "strMusicVidScreen2": null, "strMusicVidScreen3": null, "intMusicVidViews": null, "intMusicVidLikes": null, "intMusicVidDislikes": null, "intMusicVidFavorites": null, "intMusicVidComments": null, "intTrackNumber": "3", "intLoved": "0", "intScore": "10", "intScoreVotes": "3", "intTotalListeners": "92128", "intTotalPlays": "210541", "strMusicBrainzID": "38bcaeae-8d20-4574-b9a5-5eb5cf0a5c8d", "strMusicBrainzAlbumID": "e1f1dbd1-5061-30b3-8a28-f783faa1d0c6", "strMusicBrainzArtistID": "9132d515-dc0e-4494-85ae-20f06eed14f9", "strLocked": "Unlocked"}]}