{"track": [{"idTrack": "32738283", "idAlbum": "2111004", "idArtist": "111333", "idLyric": "0", "idIMVDB": null, "strTrack": "Can't Help Falling in Love", "strAlbum": "20 of the Best", "strArtist": "UB40", "strArtistAlternate": null, "intCD": null, "intDuration": "211640", "strGenre": "Reggae", "strMood": null, "strStyle": null, "strTheme": null, "strDescriptionEN": null, "strDescriptionDE": null, "strDescriptionFR": null, "strDescriptionCN": null, "strDescriptionIT": null, "strDescriptionJP": null, "strDescriptionRU": null, "strDescriptionES": null, "strDescriptionPT": null, "strDescriptionSE": null, "strDescriptionNL": null, "strDescriptionHU": null, "strDescriptionNO": null, "strDescriptionIL": null, "strDescriptionPL": null, "strTrackThumb": null, "strTrack3DCase": null, "strTrackLyrics": null, "strMusicVid": null, "strMusicVidDirector": null, "strMusicVidCompany": null, "strMusicVidScreen1": null, "strMusicVidScreen2": null, "strMusicVidScreen3": null, "intMusicVidViews": null, "intMusicVidLikes": null, "intMusicVidDislikes": null, "intMusicVidFavorites": null, "intMusicVidComments": null, "intTrackNumber": "1", "intLoved": "0", "intScore": "10", "intScoreVotes": "3", "intTotalListeners": "92509", "intTotalPlays": "372551", "strMusicBrainzID": "6ddd3701-5052-486c-8cd8-3c4f073a4796", "strMusicBrainzAlbumID": "925747f3-960a-4055-b89b-6efb3ce9e7bb", "strMusicBrainzArtistID": "7113aab7-628f-4050-ae49-dbecac110ca8", "strLocked": "Unlocked"}]}