{"track": [{"idTrack": "32794544", "idAlbum": "2115979", "idArtist": "112042", "idLyric": "502891", "idIMVDB": null, "strTrack": "Give Me One Reason", "strAlbum": "New Beginning", "strArtist": "Tracy Chapman", "strArtistAlternate": null, "intCD": null, "intDuration": "271600", "strGenre": "Acoustic", "strMood": "Gentle", "strStyle": "Rock/Pop", "strTheme": "...", "strDescriptionEN": null, "strDescriptionDE": null, "strDescriptionFR": null, "strDescriptionCN": null, "strDescriptionIT": null, "strDescriptionJP": null, "strDescriptionRU": null, "strDescriptionES": null, "strDescriptionPT": null, "strDescriptionSE": null, "strDescriptionNL": null, "strDescriptionHU": null, "strDescriptionNO": null, "strDescriptionIL": null, "strDescriptionPL": null, "strTrackThumb": null, "strTrack3DCase": null, "strTrackLyrics": null, "strMusicVid": "https://www.youtube.com/watch?v=V6hQ9HSKlIE", "strMusicVidDirector": "Julie Dash", "strMusicVidCompany": "", "strMusicVidScreen1": null, "strMusicVidScreen2": null, "strMusicVidScreen3": null, "intMusicVidViews": "36615146", "intMusicVidLikes": "338313", "intMusicVidDislikes": null, "intMusicVidFavorites": "0", "intMusicVidComments": "7742", "intTrackNumber": "9", "intLoved": "0", "intScore": "9", "intScoreVotes": "3", "intTotalListeners": "206493", "intTotalPlays": "992956", "strMusicBrainzID": "1555f27a-6b44-4978-b53e-e8cfec7f936d", "strMusicBrainzAlbumID": "9bdfd7c4-19f6-3d27-9f7a-e3d96b4fe0fc", "strMusicBrainzArtistID": "1129817c-488a-4096-80c1-77fc1b107c93", "strLocked": "Unlocked"}]}