{"track": [{"idTrack": "33635707", "idAlbum": "2184460", "idArtist": "124513", "idLyric": "271181", "idIMVDB": null, "strTrack": "Twisted", "strAlbum": "Keith Sweat", "strArtist": "Keith Sweat", "strArtistAlternate": null, "intCD": null, "intDuration": "270666", "strGenre": "R&B", "strMood": null, "strStyle": null, "strTheme": null, "strDescriptionEN": "", "strDescriptionDE": null, "strDescriptionFR": null, "strDescriptionCN": null, "strDescriptionIT": null, "strDescriptionJP": null, "strDescriptionRU": null, "strDescriptionES": null, "strDescriptionPT": null, "strDescriptionSE": null, "strDescriptionNL": null, "strDescriptionHU": null, "strDescriptionNO": null, "strDescriptionIL": null, "strDescriptionPL": null, "strTrackThumb": null, "strTrack3DCase": null, "strTrackLyrics": "", "strMusicVid": "http://www.youtube.com/watch?v=cP4yAnbtDZE", "strMusicVidDirector": "Paul Hunter", "strMusicVidCompany": "", "strMusicVidScreen1": null, "strMusicVidScreen2": null, "strMusicVidScreen3": null, "intMusicVidViews": "6590001", "intMusicVidLikes": "24872", "intMusicVidDislikes": "697", "intMusicVidFavorites": null, "intMusicVidComments": null, "intTrackNumber": "1", "intLoved": "0", "intScore": "10", "intScoreVotes": "4", "intTotalListeners": "97672", "intTotalPlays": "318327", "strMusicBrainzID": "478d317d-2533-4f96-b4db-e40b0cef58ba", "strMusicBrainzAlbumID": "20509801-4e2d-371a-bcc4-5e38681e1b5a", "strMusicBrainzArtistID": "33ecb3d1-9ece-4462-b231-ce6e7a82dd50", "strLocked": "Unlocked"}]}